Workbook

Sheet Modelo
A1: Casa Pan · Modelo de negocio v0.1
A2: Amarillo = lo pones tú. Verde = se calcula solo. Fuente de cada número: pestaña Supuestos.
A3: PRECIOS Y COSTOS
A4: Pan, precio venta directa | B4: 120
A5: Pan, precio restaurantes | B5: 110
A6: Pastry, precio por pieza | B6: 45
A7: Costo por pan (materia prima, renta, gas) | B7: 30
A8: Costo por pastry
A9: % de panes que van a restaurantes | B9: 0.3
A10: Ganancia por pan, venta directa | B10: =B4-B7
A11: Ganancia por pan, restaurantes | B11: =B5-B7
A12: Ganancia por pastry | B12: =IF(B8="","",B6-B8)
A13: Ganancia promedio por pan | B13: =B10*(1-B9)+B11*B9
A15: LO QUE NECESITAS AL MES
A16: Tu sueldo | B16: 30000
A17: Deudas (pago mensual) | B17: 0
A18: Otros gastos fijos (no incluidos en el costo por pan) | B18: 0
A19: Semanas por mes | B19: 4.3
A20: Total que necesitas al mes | B20: =SUM(B16:B18)
A22: PUNTO DE EQUILIBRIO
A23: Panes por semana para cubrirlo | B23: =ROUNDUP(B20/B19/B13,0)
A24: Panes por día de venta (días de venta por semana →) | B24: =ROUNDUP(B23/C24,0) | C24: 4
A25: Mejor temporada, panes por semana | B25: 450
A26: % de tu mejor temporada | B26: =B23/B25
A28: CAPACIDAD (solo, sin empleados)
A29: Máximo de panes que puedes hornear solo por día
A30: Días de horneado por semana | B30: 4
A31: Capacidad por semana | B31: =IF(B29="","",B29*B30)
A32: ¿Cubre el equilibrio? | B32: =IF(B31="","falta dato",IF(B31>=B23,"sí","no"))

Sheet Supuestos
A1: Dato | B1: Valor | C1: Fuente | D1: Confianza | E1: Notas
A2: Precio pan venta directa | B2: 120 | C2: Sasha, 15 oct | D2: Alta
A3: Precio pan restaurantes | B3: 110 | C3: Sasha, 15 oct | D3: Alta
A4: Precio pastry | B4: 45 | C4: Sasha, 15 oct | D4: Alta | E4: croissant, pan de chocolate
A5: Costo por pan sin sueldos | B5: 30 | C5: Benjamin, sesión 1 [37:57] | D5: Media | E5: dice que incluye renta y gas: confirmar
A6: Margen ~50% que recuerda | B6: ~60 de 120 | C6: Benjamin, S1 [38:10] | D6: Baja | E6: probablemente con sueldos
A7: % restaurantes | B7: 0.3 | C7: Estimado | D7: Baja | E7: reemplazar con datos
A8: Mejor temporada, panes/semana | B8: 400–500 | C8: Benjamin, S1 [16:19] | D8: Media
A9: Harina enero mejor temporada | B9: ~2,000 kg | C9: Benjamin, S1 [17:25] | D9: Media | E9: dijo 3 t, luego corrigió
A10: Costal harina 25 kg | B10: ~500 MXN | C10: Benjamin, S1 [36:34] | D10: Media | E10: antes ~300
A11: Temporada | B11: nov → may/jun | C11: Benjamin, S1 [39:43] | D11: Alta | E11: ~70% de la gente se va con el calor
A12: Plan vs real temporada pasada | B12: 10 → 4 | C12: Benjamin, S1 [39:23] | D12: Media
A13: Vida de la harina en el calor | B13: 7–10 días en el piso | C13: Benjamin, S1 [26:39] | D13: Media | E13: centeno/kamut tardan 10–15 días en llegar

Sheet Canales
A1: Canal | B1: Panes/semana (mejor temporada) | C1: Precio | D1: Notas | E1: Fuente
A2: Mercado San Pancho | B2: 150–170 por día de mercado | C2: 120 | D2: se acaba en ~2 h en días buenos | E2: S1 [15:54]
A3: Restaurantes locales | B3: 100–150 | C3: 110 | E3: S1 [16:19]
A4: Lo de Marcos | B4: 30–40 | C4: 110 | D4: un lugar | E4: S1 [35:01]
A5: Sayulita | B5: ~50 piezas | C5: 110 | D5: esta semana: 10 panes + 50 bagels | E5: S1 [35:01]
A6: Viernes en la tienda | B6: ~100 | C6: 120 | E6: S1 [16:19]
A7: WhatsApp | B7: ? | C7: 120 | D7: mensajes a las 10 pm | E7: S1 [53:13]
A8: Retiros | B8: ? | D8: cancelados hasta enero | E8: S1 [42:01]
A9: Airbnb / rentas | B9: ? | D9: llenos en Navidad, bajan en enero | E9: S1 [42:41]

Sheet Registro diario
A1: Una línea por producto por día de venta. Lo más valioso: la hora en que se acabó.
A2: Fecha | B2: Semana | C2: Canal | D2: Producto | E2: Horneados | F2: Vendidos | G2: Sobraron | H2: Hora en que se acabó | I2: Apuntados en la lista | J2: Ganancia ($) | K2: Pérdida por sobrante ($)
B3: =IF(A3="","",ISOWEEKNUM(A3)) | G3: =IF(E3="","",E3-F3) | J3: =IF(F3="","",(F3+I3)*IF(D3="Pastry",Modelo!$B$12,IF(C3="Restaurante",Modelo!$B$11,Modelo!$B$10))) | K3: =IF(G3="","",G3*IF(D3="Pastry",Modelo!$B$8,Modelo!$B$7))
B4: =IF(A4="","",ISOWEEKNUM(A4)) | G4: =IF(E4="","",E4-F4) | J4: =IF(F4="","",(F4+I4)*IF(D4="Pastry",Modelo!$B$12,IF(C4="Restaurante",Modelo!$B$11,Modelo!$B$10))) | K4: =IF(G4="","",G4*IF(D4="Pastry",Modelo!$B$8,Modelo!$B$7))
B5: =IF(A5="","",ISOWEEKNUM(A5)) | G5: =IF(E5="","",E5-F5) | J5: =IF(F5="","",(F5+I5)*IF(D5="Pastry",Modelo!$B$12,IF(C5="Restaurante",Modelo!$B$11,Modelo!$B$10))) | K5: =IF(G5="","",G5*IF(D5="Pastry",Modelo!$B$8,Modelo!$B$7))
B6: =IF(A6="","",ISOWEEKNUM(A6)) | G6: =IF(E6="","",E6-F6) | J6: =IF(F6="","",(F6+I6)*IF(D6="Pastry",Modelo!$B$12,IF(C6="Restaurante",Modelo!$B$11,Modelo!$B$10))) | K6: =IF(G6="","",G6*IF(D6="Pastry",Modelo!$B$8,Modelo!$B$7))
B7: =IF(A7="","",ISOWEEKNUM(A7)) | G7: =IF(E7="","",E7-F7) | J7: =IF(F7="","",(F7+I7)*IF(D7="Pastry",Modelo!$B$12,IF(C7="Restaurante",Modelo!$B$11,Modelo!$B$10))) | K7: =IF(G7="","",G7*IF(D7="Pastry",Modelo!$B$8,Modelo!$B$7))
B8: =IF(A8="","",ISOWEEKNUM(A8)) | G8: =IF(E8="","",E8-F8) | J8: =IF(F8="","",(F8+I8)*IF(D8="Pastry",Modelo!$B$12,IF(C8="Restaurante",Modelo!$B$11,Modelo!$B$10))) | K8: =IF(G8="","",G8*IF(D8="Pastry",Modelo!$B$8,Modelo!$B$7))
B9: =IF(A9="","",ISOWEEKNUM(A9)) | G9: =IF(E9="","",E9-F9) | J9: =IF(F9="","",(F9+I9)*IF(D9="Pastry",Modelo!$B$12,IF(C9="Restaurante",Modelo!$B$11,Modelo!$B$10))) | K9: =IF(G9="","",G9*IF(D9="Pastry",Modelo!$B$8,Modelo!$B$7))
B10: =IF(A10="","",ISOWEEKNUM(A10)) | G10: =IF(E10="","",E10-F10) | J10: =IF(F10="","",(F10+I10)*IF(D10="Pastry",Modelo!$B$12,IF(C10="Restaurante",Modelo!$B$11,Modelo!$B$10))) | K10: =IF(G10="","",G10*IF(D10="Pastry",Modelo!$B$8,Modelo!$B$7))
B11: =IF(A11="","",ISOWEEKNUM(A11)) | G11: =IF(E11="","",E11-F11) | J11: =IF(F11="","",(F11+I11)*IF(D11="Pastry",Modelo!$B$12,IF(C11="Restaurante",Modelo!$B$11,Modelo!$B$10))) | K11: =IF(G11="","",G11*IF(D11="Pastry",Modelo!$B$8,Modelo!$B$7))
B12: =IF(A12="","",ISOWEEKNUM(A12)) | G12: =IF(E12="","",E12-F12) | J12: =IF(F12="","",(F12+I12)*IF(D12="Pastry",Modelo!$B$12,IF(C12="Restaurante",Modelo!$B$11,Modelo!$B$10))) | K12: =IF(G12="","",G12*IF(D12="Pastry",Modelo!$B$8,Modelo!$B$7))
B13: =IF(A13="","",ISOWEEKNUM(A13)) | G13: =IF(E13="","",E13-F13) | J13: =IF(F13="","",(F13+I13)*IF(D13="Pastry",Modelo!$B$12,IF(C13="Restaurante",Modelo!$B$11,Modelo!$B$10))) | K13: =IF(G13="","",G13*IF(D13="Pastry",Modelo!$B$8,Modelo!$B$7))
B14: =IF(A14="","",ISOWEEKNUM(A14)) | G14: =IF(E14="","",E14-F14) | J14: =IF(F14="","",(F14+I14)*IF(D14="Pastry",Modelo!$B$12,IF(C14="Restaurante",Modelo!$B$11,Modelo!$B$10))) | K14: =IF(G14="","",G14*IF(D14="Pastry",Modelo!$B$8,Modelo!$B$7))
... B202: =IF(A202="","",ISOWEEKNUM(A202)) | G202: =IF(E202="","",E202-F202) | J202: =IF(F202="","",(F202+I202)*IF(D202="Pastry",Modelo!$B$12,IF(C202="Restaurante",Modelo!$B$11,Modelo!$B$10))) | K202: =IF(G202="","",G202*IF(D202="Pastry",Modelo!$B$8,Modelo!$B$7))

Sheet Compras
A1: Fecha | B1: Mes | C1: Producto | D1: Kg | E1: Precio total ($) | F1: $ por kg | G1: Proveedor
B2: =IF(A2="","",TEXT(A2,"yyyy-mm")) | F2: =IF(OR(D2="",E2=""),"",E2/D2)
B3: =IF(A3="","",TEXT(A3,"yyyy-mm")) | F3: =IF(OR(D3="",E3=""),"",E3/D3)
B4: =IF(A4="","",TEXT(A4,"yyyy-mm")) | F4: =IF(OR(D4="",E4=""),"",E4/D4)
B5: =IF(A5="","",TEXT(A5,"yyyy-mm")) | F5: =IF(OR(D5="",E5=""),"",E5/D5)
B6: =IF(A6="","",TEXT(A6,"yyyy-mm")) | F6: =IF(OR(D6="",E6=""),"",E6/D6)
B7: =IF(A7="","",TEXT(A7,"yyyy-mm")) | F7: =IF(OR(D7="",E7=""),"",E7/D7)
B8: =IF(A8="","",TEXT(A8,"yyyy-mm")) | F8: =IF(OR(D8="",E8=""),"",E8/D8)
B9: =IF(A9="","",TEXT(A9,"yyyy-mm")) | F9: =IF(OR(D9="",E9=""),"",E9/D9)
B10: =IF(A10="","",TEXT(A10,"yyyy-mm")) | F10: =IF(OR(D10="",E10=""),"",E10/D10)
B11: =IF(A11="","",TEXT(A11,"yyyy-mm")) | F11: =IF(OR(D11="",E11=""),"",E11/D11)
B12: =IF(A12="","",TEXT(A12,"yyyy-mm")) | F12: =IF(OR(D12="",E12=""),"",E12/D12)
B13: =IF(A13="","",TEXT(A13,"yyyy-mm")) | F13: =IF(OR(D13="",E13=""),"",E13/D13)
... B101: =IF(A101="","",TEXT(A101,"yyyy-mm")) | F101: =IF(OR(D101="",E101=""),"",E101/D101)

Sheet ROI
A1: Lo que cambió, en pesos. Semana base = antes de la lista y el horario de WhatsApp.
A2: Semana | B2: Horneados | C2: Vendidos | D2: % sobrante | E2: Apuntados en la lista | F2: Ganancia ($) | G2: Pérdida por sobrante ($) | H2: Ganancia extra por la lista ($)
A3: 44 | B3: =SUMIFS('Registro diario'!E$3:E$202,'Registro diario'!B$3:B$202,A3) | C3: =SUMIFS('Registro diario'!F$3:F$202,'Registro diario'!B$3:B$202,A3) | D3: =IF(B3=0,"",(B3-C3)/B3) | E3: =SUMIFS('Registro diario'!I$3:I$202,'Registro diario'!B$3:B$202,A3) | F3: =SUMIFS('Registro diario'!J$3:J$202,'Registro diario'!B$3:B$202,A3) | G3: =SUMIFS('Registro diario'!K$3:K$202,'Registro diario'!B$3:B$202,A3) | H3: =E3*Modelo!$B$10
A4: 45 | B4: =SUMIFS('Registro diario'!E$3:E$202,'Registro diario'!B$3:B$202,A4) | C4: =SUMIFS('Registro diario'!F$3:F$202,'Registro diario'!B$3:B$202,A4) | D4: =IF(B4=0,"",(B4-C4)/B4) | E4: =SUMIFS('Registro diario'!I$3:I$202,'Registro diario'!B$3:B$202,A4) | F4: =SUMIFS('Registro diario'!J$3:J$202,'Registro diario'!B$3:B$202,A4) | G4: =SUMIFS('Registro diario'!K$3:K$202,'Registro diario'!B$3:B$202,A4) | H4: =E4*Modelo!$B$10
A5: 46 | B5: =SUMIFS('Registro diario'!E$3:E$202,'Registro diario'!B$3:B$202,A5) | C5: =SUMIFS('Registro diario'!F$3:F$202,'Registro diario'!B$3:B$202,A5) | D5: =IF(B5=0,"",(B5-C5)/B5) | E5: =SUMIFS('Registro diario'!I$3:I$202,'Registro diario'!B$3:B$202,A5) | F5: =SUMIFS('Registro diario'!J$3:J$202,'Registro diario'!B$3:B$202,A5) | G5: =SUMIFS('Registro diario'!K$3:K$202,'Registro diario'!B$3:B$202,A5) | H5: =E5*Modelo!$B$10
A6: 47 | B6: =SUMIFS('Registro diario'!E$3:E$202,'Registro diario'!B$3:B$202,A6) | C6: =SUMIFS('Registro diario'!F$3:F$202,'Registro diario'!B$3:B$202,A6) | D6: =IF(B6=0,"",(B6-C6)/B6) | E6: =SUMIFS('Registro diario'!I$3:I$202,'Registro diario'!B$3:B$202,A6) | F6: =SUMIFS('Registro diario'!J$3:J$202,'Registro diario'!B$3:B$202,A6) | G6: =SUMIFS('Registro diario'!K$3:K$202,'Registro diario'!B$3:B$202,A6) | H6: =E6*Modelo!$B$10
A7: 48 | B7: =SUMIFS('Registro diario'!E$3:E$202,'Registro diario'!B$3:B$202,A7) | C7: =SUMIFS('Registro diario'!F$3:F$202,'Registro diario'!B$3:B$202,A7) | D7: =IF(B7=0,"",(B7-C7)/B7) | E7: =SUMIFS('Registro diario'!I$3:I$202,'Registro diario'!B$3:B$202,A7) | F7: =SUMIFS('Registro diario'!J$3:J$202,'Registro diario'!B$3:B$202,A7) | G7: =SUMIFS('Registro diario'!K$3:K$202,'Registro diario'!B$3:B$202,A7) | H7: =E7*Modelo!$B$10
A8: 49 | B8: =SUMIFS('Registro diario'!E$3:E$202,'Registro diario'!B$3:B$202,A8) | C8: =SUMIFS('Registro diario'!F$3:F$202,'Registro diario'!B$3:B$202,A8) | D8: =IF(B8=0,"",(B8-C8)/B8) | E8: =SUMIFS('Registro diario'!I$3:I$202,'Registro diario'!B$3:B$202,A8) | F8: =SUMIFS('Registro diario'!J$3:J$202,'Registro diario'!B$3:B$202,A8) | G8: =SUMIFS('Registro diario'!K$3:K$202,'Registro diario'!B$3:B$202,A8) | H8: =E8*Modelo!$B$10
A9: 50 | B9: =SUMIFS('Registro diario'!E$3:E$202,'Registro diario'!B$3:B$202,A9) | C9: =SUMIFS('Registro diario'!F$3:F$202,'Registro diario'!B$3:B$202,A9) | D9: =IF(B9=0,"",(B9-C9)/B9) | E9: =SUMIFS('Registro diario'!I$3:I$202,'Registro diario'!B$3:B$202,A9) | F9: =SUMIFS('Registro diario'!J$3:J$202,'Registro diario'!B$3:B$202,A9) | G9: =SUMIFS('Registro diario'!K$3:K$202,'Registro diario'!B$3:B$202,A9) | H9: =E9*Modelo!$B$10
A10: 51 | B10: =SUMIFS('Registro diario'!E$3:E$202,'Registro diario'!B$3:B$202,A10) | C10: =SUMIFS('Registro diario'!F$3:F$202,'Registro diario'!B$3:B$202,A10) | D10: =IF(B10=0,"",(B10-C10)/B10) | E10: =SUMIFS('Registro diario'!I$3:I$202,'Registro diario'!B$3:B$202,A10) | F10: =SUMIFS('Registro diario'!J$3:J$202,'Registro diario'!B$3:B$202,A10) | G10: =SUMIFS('Registro diario'!K$3:K$202,'Registro diario'!B$3:B$202,A10) | H10: =E10*Modelo!$B$10
A11: 52 | B11: =SUMIFS('Registro diario'!E$3:E$202,'Registro diario'!B$3:B$202,A11) | C11: =SUMIFS('Registro diario'!F$3:F$202,'Registro diario'!B$3:B$202,A11) | D11: =IF(B11=0,"",(B11-C11)/B11) | E11: =SUMIFS('Registro diario'!I$3:I$202,'Registro diario'!B$3:B$202,A11) | F11: =SUMIFS('Registro diario'!J$3:J$202,'Registro diario'!B$3:B$202,A11) | G11: =SUMIFS('Registro diario'!K$3:K$202,'Registro diario'!B$3:B$202,A11) | H11: =E11*Modelo!$B$10
A12: 1 | B12: =SUMIFS('Registro diario'!E$3:E$202,'Registro diario'!B$3:B$202,A12) | C12: =SUMIFS('Registro diario'!F$3:F$202,'Registro diario'!B$3:B$202,A12) | D12: =IF(B12=0,"",(B12-C12)/B12) | E12: =SUMIFS('Registro diario'!I$3:I$202,'Registro diario'!B$3:B$202,A12) | F12: =SUMIFS('Registro diario'!J$3:J$202,'Registro diario'!B$3:B$202,A12) | G12: =SUMIFS('Registro diario'!K$3:K$202,'Registro diario'!B$3:B$202,A12) | H12: =E12*Modelo!$B$10
A13: 2 | B13: =SUMIFS('Registro diario'!E$3:E$202,'Registro diario'!B$3:B$202,A13) | C13: =SUMIFS('Registro diario'!F$3:F$202,'Registro diario'!B$3:B$202,A13) | D13: =IF(B13=0,"",(B13-C13)/B13) | E13: =SUMIFS('Registro diario'!I$3:I$202,'Registro diario'!B$3:B$202,A13) | F13: =SUMIFS('Registro diario'!J$3:J$202,'Registro diario'!B$3:B$202,A13) | G13: =SUMIFS('Registro diario'!K$3:K$202,'Registro diario'!B$3:B$202,A13) | H13: =E13*Modelo!$B$10
A14: 3 | B14: =SUMIFS('Registro diario'!E$3:E$202,'Registro diario'!B$3:B$202,A14) | C14: =SUMIFS('Registro diario'!F$3:F$202,'Registro diario'!B$3:B$202,A14) | D14: =IF(B14=0,"",(B14-C14)/B14) | E14: =SUMIFS('Registro diario'!I$3:I$202,'Registro diario'!B$3:B$202,A14) | F14: =SUMIFS('Registro diario'!J$3:J$202,'Registro diario'!B$3:B$202,A14) | G14: =SUMIFS('Registro diario'!K$3:K$202,'Registro diario'!B$3:B$202,A14) | H14: =E14*Modelo!$B$10
... A32: 21 | B32: =SUMIFS('Registro diario'!E$3:E$202,'Registro diario'!B$3:B$202,A32) | C32: =SUMIFS('Registro diario'!F$3:F$202,'Registro diario'!B$3:B$202,A32) | D32: =IF(B32=0,"",(B32-C32)/B32) | E32: =SUMIFS('Registro diario'!I$3:I$202,'Registro diario'!B$3:B$202,A32) | F32: =SUMIFS('Registro diario'!J$3:J$202,'Registro diario'!B$3:B$202,A32) | G32: =SUMIFS('Registro diario'!K$3:K$202,'Registro diario'!B$3:B$202,A32) | H32: =E32*Modelo!$B$10
